bgparsers/__init__.py
bgparsers/selector.py
bgparsers/utils.py
bgparsers/commands/__init__.py
bgparsers/commands/bgvariants.py
bgparsers/commands/tasks/__init__.py
bgparsers/commands/tasks/cat.py
bgparsers/commands/tasks/count.py
bgparsers/commands/tasks/preprocess.py
bgparsers/commands/tasks/script.py
bgparsers/readers/__init__.py
bgparsers/readers/common.py
bgparsers/readers/elements.py
bgparsers/readers/tsv.py
bgparsers/readers/variants.py
tests/__init__.py
tests/test_bginfo.py
tests/test_total_lines.py
bgparsers-0.10.dist-info/LICENSE
bgparsers-0.10.dist-info/METADATA
bgparsers-0.10.dist-info/WHEEL
bgparsers-0.10.dist-info/entry_points.txt
bgparsers-0.10.dist-info/top_level.txt
bgparsers-0.10.dist-info/RECORD
